channels_redux/__init__.py
channels_redux/app_settings.py
channels_redux/apps.py
channels_redux/notify.py
channels_redux/rest.py
channels_redux/settings.py
channels_redux/signals.py
channels_redux/views.py
channels_redux/templates/react/react_full.html
channels_redux/templates/react/react_root.html
channels_redux/templates/react/react_scripts.html
channels_redux/templatetags/__init__.py
channels_redux/templatetags/react.py
channels_redux-1.8.0.dist-info/METADATA
channels_redux-1.8.0.dist-info/RECORD
channels_redux-1.8.0.dist-info/WHEEL
channels_redux-1.8.0.dist-info/top_level.txt
