Metadata-Version: 2.1
Name: channels-redux
Version: 1.8.0
Summary: Channels-Redux is a package that notifies subscribers about changes in the database
Home-page: https://bitbucket.org/plus1tables/channels-redux-python/
Author: Johnathan Ryan Hornik
Author-email: ryanhornik@gmail.com
License: MIT License
Platform: UNKNOWN
Classifier: Environment :: Web Environment
Classifier: Framework :: Django
Classifier: Framework :: Django :: 1.11
Classifier: Intended Audience :: Developers
Classifier: Programming Language :: Python
Classifier: Programming Language :: Python :: 3
Classifier: Programming Language :: Python :: 3.4
Classifier: Programming Language :: Python :: 3.5
Classifier: License :: OSI Approved :: MIT License
Classifier: Operating System :: OS Independent
Classifier: Topic :: Internet :: WWW/HTTP
Classifier: Topic :: Internet :: WWW/HTTP :: Dynamic Content
Requires-Dist: Django (>=1.11)
Requires-Dist: djangorestframework (>=3.4.0)
Requires-Dist: channels (>=2.0.0)
